{
  "label": "Modbus",
  "position": 1,
  "link": {
    "type": "generated-index",
    "description": "Примерни проекти, използващи Modbus протокола за комуникация между множество ESP32 модули в Master-Slave конфигурация. Тези проекти демонстрират как чрез протокола Modbus могат да се обменят данни между устройства в различни роли – master и slave. Modbus е надежден индустриален протокол, който се използва широко за автоматизация на процеси и управление на системи. Приложен към ESP32, той предоставя възможност за гъвкаво и ефективно решение за комуникация в различни мрежови архитектури. Тези примери обхващат както хардуерните, така и софтуерните аспекти на внедряване на Modbus комуникация, илюстрирайки добри практики за създаване на свързани системи."
  }
}
